kuryana/__init__.py
kuryana/async_client.py
kuryana/base.py
kuryana/client.py
kuryana/tests/test_async_client.py
kuryana/tests/test_client.py
kuryana/types/drama.py
kuryana/types/drama_cast.py
kuryana/types/drama_episodes.py
kuryana/types/drama_reviews.py
kuryana/types/index.py
kuryana/types/list.py
kuryana/types/people.py
kuryana/types/search.py
kuryana/types/seasonal_drama.py
kuryana/types/user.py
kuryana-0.2.0.dist-info/WHEEL
kuryana-0.2.0.dist-info/METADATA
kuryana-0.2.0.dist-info/RECORD
