Metadata-Version: 2.3
Name: kuryana
Version: 0.2.0
Summary: Python library for [Kuryana](https://github.com/tbdsux/kuryana) API.
Author: Joshue Abance
Author-email: Joshue Abance <iamcoderx@gmail.com>
Requires-Dist: httpx>=0.28.1
Requires-Dist: pydantic>=2.12.4
Requires-Python: >=3.12
